annotator_store/__init__.py
annotator_store/admin.py
annotator_store/apps.py
annotator_store/models.py
annotator_store/test_urls.py
annotator_store/tests.py
annotator_store/urls.py
annotator_store/utils.py
annotator_store/views.py
annotator_store/management/__init__.py
annotator_store/management/commands/__init__.py
annotator_store/management/commands/import_annotations.py
annotator_store/migrations/0001_initial.py
annotator_store/migrations/0002_annotation_quote_text_optional.py
annotator_store/migrations/__init__.py
annotator_store/static/ext/annotator/annotator.min.css
annotator_store/static/ext/annotator/annotator.min.js
annotator_store/static/ext/annotator/img/annotator-glyph-sprite.png
annotator_store/static/ext/annotator/img/annotator-icon-sprite.png
annotator_store/static/ext/font-awesome/css/font-awesome.css
annotator_store/static/ext/font-awesome/css/font-awesome.min.css
annotator_store/static/ext/font-awesome/fonts/FontAwesome.otf
annotator_store/static/ext/font-awesome/fonts/fontawesome-webfont.eot
annotator_store/static/ext/font-awesome/fonts/fontawesome-webfont.svg
annotator_store/static/ext/font-awesome/fonts/fontawesome-webfont.ttf
annotator_store/static/ext/font-awesome/fonts/fontawesome-webfont.woff
annotator_store/static/ext/font-awesome/fonts/fontawesome-webfont.woff2
annotator_store/static/ext/font-awesome/less/animated.less
annotator_store/static/ext/font-awesome/less/bordered-pulled.less
annotator_store/static/ext/font-awesome/less/core.less
annotator_store/static/ext/font-awesome/less/fixed-width.less
annotator_store/static/ext/font-awesome/less/font-awesome.less
annotator_store/static/ext/font-awesome/less/icons.less
annotator_store/static/ext/font-awesome/less/larger.less
annotator_store/static/ext/font-awesome/less/list.less
annotator_store/static/ext/font-awesome/less/mixins.less
annotator_store/static/ext/font-awesome/less/path.less
annotator_store/static/ext/font-awesome/less/rotated-flipped.less
annotator_store-0.6.0.dist-info/DESCRIPTION.rst
annotator_store-0.6.0.dist-info/METADATA
annotator_store-0.6.0.dist-info/RECORD
annotator_store-0.6.0.dist-info/WHEEL
annotator_store-0.6.0.dist-info/metadata.json
annotator_store-0.6.0.dist-info/top_level.txt
