Metadata-Version: 2.0
Name: annotator-store
Version: 0.6.0
Summary: Django application to act as an annotator.js 2.x annotator-store backend
Home-page: https://github.com/Princeton-CDH/django-annotator-store
Author: CDH @ Princeton
Author-email: digitalhumanities@princeton.edu
License: Apache License, Version 2.0
Platform: UNKNOWN
Classifier: Environment :: Web Environment
Classifier: Framework :: Django
Classifier: Framework :: Django :: 1.8
Classifier: Framework :: Django :: 1.9
Classifier: Framework :: Django :: 1.10
Classifier: Framework :: Django :: 1.10
Classifier: Framework :: Django :: 1.11
Classifier: Intended Audience :: Developers
Classifier: License :: OSI Approved :: Apache Software License
Classifier: Operating System :: OS Independent
Classifier: Programming Language :: Python
Classifier: Programming Language :: Python :: 2
Classifier: Programming Language :: Python :: 2.7
Classifier: Programming Language :: Python :: 3
Classifier: Programming Language :: Python :: 3.5
Classifier: Development Status :: 3 - Alpha
Requires-Dist: django (>1.8)
Requires-Dist: eulcommon
Requires-Dist: jsonfield
Requires-Dist: pytz
Requires-Dist: six
Provides-Extra: docs
Requires-Dist: sphinx; extra == 'docs'
Provides-Extra: permissions
Requires-Dist: django-guardian; extra == 'permissions'
Provides-Extra: test
Requires-Dist: mock; extra == 'test'
Requires-Dist: pytest; extra == 'test'
Requires-Dist: pytest-cov; extra == 'test'
Requires-Dist: pytest-django; extra == 'test'
